ttlser/__init__.py
ttlser/serializers.py
ttlser/ttlfmt.py
ttlser/utils.py
ttlser-1.1.7.data/data/share/ttlser/good.ttl
ttlser-1.1.7.data/data/share/ttlser/nasty.ttl
ttlser-1.1.7.dist-info/licenses/LICENSE
ttlser-1.1.7.dist-info/METADATA
ttlser-1.1.7.dist-info/WHEEL
ttlser-1.1.7.dist-info/entry_points.txt
ttlser-1.1.7.dist-info/top_level.txt
ttlser-1.1.7.dist-info/RECORD
