Metadata-Version: 2.4
Name: ttlser
Version: 1.1.7
Summary: Deterministic turtle serialization for rdflib.
Home-page: https://github.com/tgbugs/pyontutils/tree/master/ttlser
Author: Tom Gillespie
Author-email: tgbugs@gmail.com
License: MIT
Keywords: rdflib rdf deterministic turtle ttl
Classifier: Development Status :: 5 - Production/Stable
Classifier: License :: OSI Approved :: MIT License
Classifier: Programming Language :: Python :: 3.7
Classifier: Programming Language :: Python :: 3.8
Classifier: Programming Language :: Python :: 3.9
Classifier: Programming Language :: Python :: 3.10
Classifier: Programming Language :: Python :: 3.11
Classifier: Programming Language :: Python :: 3.12
Classifier: Programming Language :: Python :: 3.13
Classifier: Programming Language :: Python :: Implementation :: CPython
Classifier: Programming Language :: Python :: Implementation :: PyPy
Classifier: Operating System :: POSIX :: Linux
Classifier: Operating System :: MacOS :: MacOS X
Classifier: Operating System :: Microsoft :: Windows
Requires-Python: >=3.7
License-File: LICENSE
Requires-Dist: rdflib>=6.0.2
Provides-Extra: dev
Requires-Dist: pytest-cov; extra == "dev"
Requires-Dist: wheel; extra == "dev"
Provides-Extra: ttlfmt
Requires-Dist: docopt; extra == "ttlfmt"
Requires-Dist: joblib; extra == "ttlfmt"
Provides-Extra: test
Requires-Dist: pytest; extra == "test"
Requires-Dist: docopt; extra == "test"
Requires-Dist: joblib; extra == "test"
Dynamic: author
Dynamic: author-email
Dynamic: classifier
Dynamic: description
Dynamic: description-content-type
Dynamic: home-page
Dynamic: keywords
Dynamic: license
Dynamic: license-file
Dynamic: provides-extra
Dynamic: requires-dist
Dynamic: requires-python
Dynamic: summary
